nonstandardcode/__init__.py
nonstandardcode/ingest_data.py
nonstandardcode/score.py
nonstandardcode/train.py
nonstandardcode-0.0.1.dist-info/METADATA
nonstandardcode-0.0.1.dist-info/WHEEL
nonstandardcode-0.0.1.dist-info/top_level.txt
nonstandardcode-0.0.1.dist-info/RECORD
