Metadata-Version: 2.1
Name: nonstandardcode
Version: 0.0.1
Summary: ML Project to predict median house value on given housing data
Author: Balaji Putta Mohan
Author-email: balaji.mohan@tigeranalytics.com
Maintainer: Balaji Putta Mohan
Requires-Dist: black (>=21.12b0)
Requires-Dist: isort (>=5.0.0)
Requires-Dist: flake8 (>=4.0.0)
Requires-Dist: numpy (>=1.20.0)
Requires-Dist: pandas (>=1.3.0)
Requires-Dist: scipy (>=1.0.0)
Requires-Dist: scikit-learn (>=1.0.0)
